remla/__init__.py
remla/customvalidators.py
remla/i2ccmd.py
remla/labcontrol/Controllers.py
remla/labcontrol/Experiment.py
remla/labcontrol/__init__.py
remla/labcontrol/test.json
remla/main.py
remla/settings.py
remla/setup/finalInfoTemplate.md
remla/setup/hello.txt
remla/setup/i2c-output.png
remla/setup/index.html
remla/setup/localhost.conf
remla/setup/mediaMTXGetFeed.js
remla/setup/mediamtx.service
remla/setup/mediamtx.yml
remla/setup/reader.js
remla/setup/remlaSocket.js
remla/setup/remlaSocket_BACKUP_5176.js
remla/setup/remlaSocket_BASE_5176.js
remla/setup/remlaSocket_LOCAL_5176.js
remla/setup/remlaSocket_REMOTE_5176.js
remla/setupcmd.py
remla/systemHelpers.py
remla/typerHelpers.py
remla/yaml.py
remla-0.3.1.dist-info/METADATA
remla-0.3.1.dist-info/WHEEL
remla-0.3.1.dist-info/entry_points.txt
remla-0.3.1.dist-info/RECORD
