Metadata-Version: 2.4
Name: remla
Version: 0.3.1
Summary: 
Author: Zak Espley
Author-email: zespley@gmail.com
Requires-Python: >=3.11,<4.0
Classifier: Programming Language :: Python :: 3
Classifier: Programming Language :: Python :: 3.11
Classifier: Programming Language :: Python :: 3.12
Classifier: Programming Language :: Python :: 3.13
Classifier: Programming Language :: Python :: 3.14
Requires-Dist: adafruit-circuitpython-motorkit (>=1.6.14,<2.0.0)
Requires-Dist: click (>=8.1.3,<8.2)
Requires-Dist: dlipower (>=1.0.176,<2.0.0)
Requires-Dist: pathvalidate (>=3.2.0,<4.0.0)
Requires-Dist: pigpio (>=1.78,<2.0)
Requires-Dist: psutil (>=5.9.4,<6.0.0)
Requires-Dist: python-tplink-smarthome (>=0.1.3,<0.2.0)
Requires-Dist: pyvisa (>=1.14.1,<2.0.0)
Requires-Dist: pyvisa-py (>=0.7.2,<0.8.0)
Requires-Dist: rpistepper (>=0.3a1,<0.4)
Requires-Dist: ruamel-yaml (>=0.18.6,<0.19.0)
Requires-Dist: setuptools (>=70.0.0,<71.0.0)
Requires-Dist: typer[all] (>=0.12.1,<0.13.0)
Requires-Dist: validators (>=0.28.3,<0.29.0)
Requires-Dist: websockets (>=12.0,<13.0)
Requires-Dist: wheel (>=0.43.0,<0.44.0)
